deepsearchkit/__init__.py
deepsearchkit/core.py
deepsearchkit/error_handler.py
deepsearchkit/indexer.py
deepsearchkit-1.0.1.dist-info/METADATA
deepsearchkit-1.0.1.dist-info/WHEEL
deepsearchkit-1.0.1.dist-info/top_level.txt
deepsearchkit-1.0.1.dist-info/RECORD
