Metadata-Version: 2.1
Name: deepsearchkit
Version: 1.0.1
Summary: A small, fast, and easy package for semantic searching using artificial intelligence.
Home-page: https://github.com/fakerybakery/deepsearchkit
Author: mrfakename
Author-email: me@mrfake.name
Requires-Dist: txtai
Requires-Dist: tqdm
